setup.py
ETipsService.egg-info/PKG-INFO
ETipsService.egg-info/SOURCES.txt
ETipsService.egg-info/dependency_links.txt
ETipsService.egg-info/requires.txt
ETipsService.egg-info/top_level.txt
service/_.py
service/__init__.py
service/lifeService.py
service/subsystem.py
service/wyulibrary.py
service/wyunews.py
test/__init__.py
test/test_lifeservice.py
test/test_subsystem.py
test/test_wyulibrary.py
test/test_wyunews.py