Metadata-Version: 1.1
Name: ETipsService
Version: 1.0.6
Summary: service lib for ETips
Home-page: https://github.com/Jayin/ETipsService
Author: Jayin Ton
Author-email: tonjayin@gmail.com
License: Apache License, Version 2.0
Keywords: ETips
Platform: UNKNOWN
Classifier: Development Status :: 4 - Beta
Classifier: License :: OSI Approved :: Apache Software License
Classifier: Programming Language :: Python
Classifier: Programming Language :: Python :: 3
Classifier: Programming Language :: Python :: 2.7
Classifier: Environment :: Other Environment
Classifier: Intended Audience :: Developers
Classifier: Operating System :: OS Independent
